<?xml version="1.0" encoding="utf-8"?>
<!--
- phpMyAdmin XML Dump
- version 4.5.1
- https://www.phpmyadmin.net
-
- Host: 127.0.0.1
- Generation Time: Dec 04, 2015 at 10:49 PM
- Server version: 10.1.8-MariaDB
- PHP Version: 5.5.30
-->

<pma_xml_export version="1.0" xmlns:pma="http://www.phpmyadmin.net/some_doc_url/">
    <!--
    - Structure schemas
    -->
    <pma:structure_schemas>
        <pma:database name="train" collation="latin1_swedish_ci" charset="latin1">
            <pma:table name="purchase">
                CREATE TABLE `purchase` (
                  `purchase_ID` int(11) NOT NULL AUTO_INCREMENT,
                  `time_stamp` datetime NOT NULL,
                  `username` varchar(40) NOT NULL,
                  `fee` double NOT NULL,
                  `type` varchar(10) NOT NULL,
                  PRIMARY KEY (`purchase_ID`)
                ) ENGINE=InnoDB AUTO_INCREMENT=39 DEFAULT CHARSET=latin1;
            </pma:table>
            <pma:table name="stations">
                CREATE TABLE `stations` (
                  `line` varchar(30) NOT NULL,
                  `station` varchar(30) NOT NULL,
                  PRIMARY KEY (`station`)
                ) ENGINE=InnoDB DEFAULT CHARSET=latin1;
            </pma:table>
            <pma:table name="times">
                CREATE TABLE `times` (
                  `station` varchar(30) NOT NULL,
                  `direction` varchar(30) NOT NULL,
                  `times_string` varchar(256) NOT NULL,
                  KEY `station` (`station`),
                  CONSTRAINT `times_ibfk_1` FOREIGN KEY (`station`) REFERENCES `stations` (`station`)
                ) ENGINE=InnoDB DEFAULT CHARSET=latin1;
            </pma:table>
            <pma:table name="users">
                CREATE TABLE `users` (
                  `firstname` varchar(30) NOT NULL,
                  `lastname` varchar(30) NOT NULL,
                  `address` varchar(50) NOT NULL,
                  `city` varchar(30) NOT NULL,
                  `province` varchar(20) NOT NULL,
                  `postal` varchar(10) NOT NULL,
                  `email` varchar(20) NOT NULL,
                  `phone1` varchar(12) NOT NULL,
                  `phone2` varchar(12) DEFAULT NULL,
                  `birthday` date NOT NULL,
                  `username` varchar(20) NOT NULL,
                  `password` varchar(20) NOT NULL,
                  `cpassword` varchar(20) NOT NULL,
                  `zone` tinyint(1) NOT NULL,
                  `carpool` tinyint(1) DEFAULT NULL,
                  `carpoolBuddies` text,
                  PRIMARY KEY (`username`)
                ) ENGINE=InnoDB DEFAULT CHARSET=latin1;
            </pma:table>
        </pma:database>
    </pma:structure_schemas>

    <!--
    - Database: 'train'
    -->
    <database name="train">
        <!-- Table purchase -->
        <table name="purchase">
            <column name="purchase_ID">5</column>
            <column name="time_stamp">2015-12-04 04:13:43</column>
            <column name="username">lenmor</column>
            <column name="fee">2.75</column>
            <column name="type">Single</column>
        </table>
        <table name="purchase">
            <column name="purchase_ID">6</column>
            <column name="time_stamp">2015-12-04 04:13:44</column>
            <column name="username">lenmor</column>
            <column name="fee">2.75</column>
            <column name="type">Single</column>
        </table>
        <table name="purchase">
            <column name="purchase_ID">7</column>
            <column name="time_stamp">2015-12-04 04:13:46</column>
            <column name="username">lenmor</column>
            <column name="fee">11</column>
            <column name="type">Booklet</column>
        </table>
        <table name="purchase">
            <column name="purchase_ID">8</column>
            <column name="time_stamp">2015-12-04 04:13:48</column>
            <column name="username">lenmor</column>
            <column name="fee">2.75</column>
            <column name="type">Single</column>
        </table>
        <table name="purchase">
            <column name="purchase_ID">9</column>
            <column name="time_stamp">2015-12-04 04:21:13</column>
            <column name="username">lenmor</column>
            <column name="fee">11</column>
            <column name="type">Booklet</column>
        </table>
        <table name="purchase">
            <column name="purchase_ID">10</column>
            <column name="time_stamp">2015-12-04 04:21:17</column>
            <column name="username">lenmor</column>
            <column name="fee">11</column>
            <column name="type">Booklet</column>
        </table>
        <table name="purchase">
            <column name="purchase_ID">11</column>
            <column name="time_stamp">2015-12-04 04:21:19</column>
            <column name="username">lenmor</column>
            <column name="fee">2.75</column>
            <column name="type">Single</column>
        </table>
        <table name="purchase">
            <column name="purchase_ID">12</column>
            <column name="time_stamp">2015-12-04 04:21:21</column>
            <column name="username">lenmor</column>
            <column name="fee">11</column>
            <column name="type">Booklet</column>
        </table>
        <table name="purchase">
            <column name="purchase_ID">13</column>
            <column name="time_stamp">2015-12-04 06:30:51</column>
            <column name="username">lenmor</column>
            <column name="fee">2.75</column>
            <column name="type">Single</column>
        </table>
        <table name="purchase">
            <column name="purchase_ID">14</column>
            <column name="time_stamp">2015-12-04 09:47:02</column>
            <column name="username">Demostenis</column>
            <column name="fee">2.75</column>
            <column name="type">Single</column>
        </table>
        <table name="purchase">
            <column name="purchase_ID">15</column>
            <column name="time_stamp">2015-12-04 09:47:04</column>
            <column name="username">Demostenis</column>
            <column name="fee">2.75</column>
            <column name="type">Single</column>
        </table>
        <table name="purchase">
            <column name="purchase_ID">16</column>
            <column name="time_stamp">2015-12-04 09:47:04</column>
            <column name="username">Demostenis</column>
            <column name="fee">2.75</column>
            <column name="type">Single</column>
        </table>
        <table name="purchase">
            <column name="purchase_ID">17</column>
            <column name="time_stamp">2015-12-04 09:47:05</column>
            <column name="username">Demostenis</column>
            <column name="fee">2.75</column>
            <column name="type">Single</column>
        </table>
        <table name="purchase">
            <column name="purchase_ID">18</column>
            <column name="time_stamp">2015-12-04 09:47:05</column>
            <column name="username">Demostenis</column>
            <column name="fee">2.75</column>
            <column name="type">Single</column>
        </table>
        <table name="purchase">
            <column name="purchase_ID">19</column>
            <column name="time_stamp">2015-12-04 09:47:08</column>
            <column name="username">Demostenis</column>
            <column name="fee">11</column>
            <column name="type">Booklet</column>
        </table>
        <table name="purchase">
            <column name="purchase_ID">20</column>
            <column name="time_stamp">2015-12-04 09:47:08</column>
            <column name="username">Demostenis</column>
            <column name="fee">2.75</column>
            <column name="type">Single</column>
        </table>
        <table name="purchase">
            <column name="purchase_ID">21</column>
            <column name="time_stamp">2015-12-04 09:47:08</column>
            <column name="username">Demostenis</column>
            <column name="fee">2.75</column>
            <column name="type">Single</column>
        </table>
        <table name="purchase">
            <column name="purchase_ID">22</column>
            <column name="time_stamp">2015-12-04 09:47:13</column>
            <column name="username">Demostenis</column>
            <column name="fee">2.75</column>
            <column name="type">Single</column>
        </table>
        <table name="purchase">
            <column name="purchase_ID">23</column>
            <column name="time_stamp">2015-12-04 09:47:14</column>
            <column name="username">Demostenis</column>
            <column name="fee">2.75</column>
            <column name="type">Single</column>
        </table>
        <table name="purchase">
            <column name="purchase_ID">24</column>
            <column name="time_stamp">2015-12-04 09:47:29</column>
            <column name="username">Demostenis</column>
            <column name="fee">11</column>
            <column name="type">Booklet</column>
        </table>
        <table name="purchase">
            <column name="purchase_ID">25</column>
            <column name="time_stamp">2015-12-04 10:20:49</column>
            <column name="username">jachan</column>
            <column name="fee">11</column>
            <column name="type">Booklet</column>
        </table>
        <table name="purchase">
            <column name="purchase_ID">26</column>
            <column name="time_stamp">2015-12-04 10:23:36</column>
            <column name="username">jachan</column>
            <column name="fee">11</column>
            <column name="type">Booklet</column>
        </table>
        <table name="purchase">
            <column name="purchase_ID">27</column>
            <column name="time_stamp">2015-12-04 10:23:40</column>
            <column name="username">jachan</column>
            <column name="fee">11</column>
            <column name="type">Booklet</column>
        </table>
        <table name="purchase">
            <column name="purchase_ID">28</column>
            <column name="time_stamp">2015-12-04 10:27:52</column>
            <column name="username">stephc</column>
            <column name="fee">4.5</column>
            <column name="type">Single</column>
        </table>
        <table name="purchase">
            <column name="purchase_ID">29</column>
            <column name="time_stamp">2015-12-04 10:27:56</column>
            <column name="username">stephc</column>
            <column name="fee">4.5</column>
            <column name="type">Single</column>
        </table>
        <table name="purchase">
            <column name="purchase_ID">30</column>
            <column name="time_stamp">2015-12-04 10:27:58</column>
            <column name="username">stephc</column>
            <column name="fee">4.5</column>
            <column name="type">Single</column>
        </table>
        <table name="purchase">
            <column name="purchase_ID">31</column>
            <column name="time_stamp">2015-12-04 10:27:59</column>
            <column name="username">stephc</column>
            <column name="fee">18.5</column>
            <column name="type">Booklet</column>
        </table>
        <table name="purchase">
            <column name="purchase_ID">33</column>
            <column name="time_stamp">2015-12-04 10:30:18</column>
            <column name="username">mandymm</column>
            <column name="fee">6.5</column>
            <column name="type">Single</column>
        </table>
        <table name="purchase">
            <column name="purchase_ID">34</column>
            <column name="time_stamp">2015-12-04 10:30:21</column>
            <column name="username">mandymm</column>
            <column name="fee">25.75</column>
            <column name="type">Booklet</column>
        </table>
        <table name="purchase">
            <column name="purchase_ID">35</column>
            <column name="time_stamp">2015-12-04 10:40:47</column>
            <column name="username">marie23</column>
            <column name="fee">3.25</column>
            <column name="type">Single</column>
        </table>
        <table name="purchase">
            <column name="purchase_ID">36</column>
            <column name="time_stamp">2015-12-04 10:40:49</column>
            <column name="username">marie23</column>
            <column name="fee">13</column>
            <column name="type">Booklet</column>
        </table>
        <table name="purchase">
            <column name="purchase_ID">37</column>
            <column name="time_stamp">2015-12-04 10:40:54</column>
            <column name="username">marie23</column>
            <column name="fee">13</column>
            <column name="type">Booklet</column>
        </table>
        <table name="purchase">
            <column name="purchase_ID">38</column>
            <column name="time_stamp">2015-12-04 10:40:55</column>
            <column name="username">marie23</column>
            <column name="fee">3.25</column>
            <column name="type">Single</column>
        </table>
        <!-- Table stations -->
        <table name="stations">
            <column name="line">Vaudreuil-Hudson</column>
            <column name="station">Baie-D'Urfe</column>
        </table>
        <table name="stations">
            <column name="line">Vaudreuil-Hudson</column>
            <column name="station">Beaconsfield</column>
        </table>
        <table name="stations">
            <column name="line">Vaudreuil-Hudson</column>
            <column name="station">Beaurepaire</column>
        </table>
        <table name="stations">
            <column name="line">Deux-Montagnes</column>
            <column name="station">Bois-Franc</column>
        </table>
        <table name="stations">
            <column name="line">Deux-Montagnes</column>
            <column name="station">Canora</column>
        </table>
        <table name="stations">
            <column name="line">Vaudreuil-Hudson</column>
            <column name="station">Cedar Park</column>
        </table>
        <table name="stations">
            <column name="line">Deux-Montagnes</column>
            <column name="station">Deux-Montagnes</column>
        </table>
        <table name="stations">
            <column name="line">Vaudreuil-Hudson</column>
            <column name="station">Dorion</column>
        </table>
        <table name="stations">
            <column name="line">Vaudreuil-Hudson</column>
            <column name="station">Dorval</column>
        </table>
        <table name="stations">
            <column name="line">Deux-Montagnes</column>
            <column name="station">Du Ruisseau</column>
        </table>
        <table name="stations">
            <column name="line">Deux-Montagnes</column>
            <column name="station">Gare Centrale</column>
        </table>
        <table name="stations">
            <column name="line">Deux-Montagnes</column>
            <column name="station">Grand-Moulin</column>
        </table>
        <table name="stations">
            <column name="line">Vaudreuil-Hudson</column>
            <column name="station">Hudson</column>
        </table>
        <table name="stations">
            <column name="line">Deux-Montagnes</column>
            <column name="station">Ile-Bigras</column>
        </table>
        <table name="stations">
            <column name="line">Vaudreuil-Hudson</column>
            <column name="station">Ile-Perrot</column>
        </table>
        <table name="stations">
            <column name="line">Vaudreuil-Hudson</column>
            <column name="station">Lachine</column>
        </table>
        <table name="stations">
            <column name="line">Vaudreuil-Hudson</column>
            <column name="station">Lucien-L'Allier</column>
        </table>
        <table name="stations">
            <column name="line">Deux-Montagnes</column>
            <column name="station">Mont-Royal</column>
        </table>
        <table name="stations">
            <column name="line">Deux-Montagnes</column>
            <column name="station">Montpelier</column>
        </table>
        <table name="stations">
            <column name="line">Vaudreuil-Hudson</column>
            <column name="station">Montreal-Ouest</column>
        </table>
        <table name="stations">
            <column name="line">Vaudreuil-Hudson</column>
            <column name="station">Pincourt–Terrasse-Vaudreuil</column>
        </table>
        <table name="stations">
            <column name="line">Vaudreuil-Hudson</column>
            <column name="station">Pine Beach</column>
        </table>
        <table name="stations">
            <column name="line">Vaudreuil-Hudson</column>
            <column name="station">Pointe-Claire</column>
        </table>
        <table name="stations">
            <column name="line">Deux-Montagnes</column>
            <column name="station">Roxboro-Pierrefonds</column>
        </table>
        <table name="stations">
            <column name="line">Deux-Montagnes</column>
            <column name="station">Saint-Dorothee</column>
        </table>
        <table name="stations">
            <column name="line">Vaudreuil-Hudson</column>
            <column name="station">Sainte-Anne-de-Bellevue</column>
        </table>
        <table name="stations">
            <column name="line">Deux-Montagnes</column>
            <column name="station">Sunnybrooke</column>
        </table>
        <table name="stations">
            <column name="line">Vaudreuil-Hudson</column>
            <column name="station">Valois</column>
        </table>
        <table name="stations">
            <column name="line">Vaudreuil-Hudson</column>
            <column name="station">Vaudreuil</column>
        </table>
        <table name="stations">
            <column name="line">Vaudreuil-Hudson</column>
            <column name="station">Vendome</column>
        </table>
        <!-- Table times -->
        <table name="times">
            <column name="station">Gare Centrale</column>
            <column name="direction">Deux-Montagnes</column>
            <column name="times_string">00h30,06h45,08h45,09h30,10h30,11h30,12h30,13h30,14h30,15h00,15h45,16h05,16h30,16h50,17h10,18h20,19h05,19h30,20h30,21h30,22h30,23h30,23h45,23h50,23h55</column>
        </table>
        <table name="times">
            <column name="station">Canora</column>
            <column name="direction">Deux-Montagnes</column>
            <column name="times_string">00h30,06h45,08h45,09h30,10h30,11h30,12h30,13h30,14h30,15h00,15h45,16h05,16h30,16h50,17h10,18h20,19h05,19h30,20h30,21h30,22h30,23h30,23h45,23h50,23h55</column>
        </table>
        <table name="times">
            <column name="station">Mont-Royal</column>
            <column name="direction">Deux-Montagnes</column>
            <column name="times_string">00h30,06h45,08h45,09h30,10h30,11h30,12h30,13h30,14h30,15h00,15h45,16h05,16h30,16h50,17h10,18h20,19h05,19h30,20h30,21h30,22h30,23h30,23h45,23h50,23h55</column>
        </table>
        <table name="times">
            <column name="station">Montpelier</column>
            <column name="direction">Deux-Montagnes</column>
            <column name="times_string">00h30,06h45,08h45,09h30,10h30,11h30,12h30,13h30,14h30,15h00,15h45,16h05,16h30,16h50,17h10,18h20,19h05,19h30,20h30,21h30,22h30,23h30,23h45,23h50,23h55</column>
        </table>
        <table name="times">
            <column name="station">Du Ruisseau</column>
            <column name="direction">Deux-Montagnes</column>
            <column name="times_string">00h30,06h45,08h45,09h30,10h30,11h30,12h30,13h30,14h30,15h00,15h45,16h05,16h30,16h50,17h10,18h20,19h05,19h30,20h30,21h30,22h30,23h30,23h45,23h50,23h55</column>
        </table>
        <table name="times">
            <column name="station">Bois-Franc</column>
            <column name="direction">Deux-Montagnes</column>
            <column name="times_string">00h30,06h45,08h45,09h30,10h30,11h30,12h30,13h30,14h30,15h00,15h45,16h05,16h30,16h50,17h10,18h20,19h05,19h30,20h30,21h30,22h30,23h30,23h45,23h50,23h55</column>
        </table>
        <table name="times">
            <column name="station">Sunnybrooke</column>
            <column name="direction">Deux-Montagnes</column>
            <column name="times_string">00h30,06h45,08h45,09h30,10h30,11h30,12h30,13h30,14h30,15h00,15h45,16h05,16h30,16h50,17h10,18h20,19h05,19h30,20h30,21h30,22h30,23h30,23h45,23h50,23h55</column>
        </table>
        <table name="times">
            <column name="station">Roxboro-Pierrefonds</column>
            <column name="direction">Deux-Montagnes</column>
            <column name="times_string">00h30,06h45,08h45,09h30,10h30,11h30,12h30,13h30,14h30,15h00,15h45,16h05,16h30,16h50,17h10,18h20,19h05,19h30,20h30,21h30,22h30,23h30,23h45,23h50,23h55</column>
        </table>
        <table name="times">
            <column name="station">Ile-Bigras</column>
            <column name="direction">Deux-Montagnes</column>
            <column name="times_string">00h30,06h45,08h45,09h30,10h30,11h30,12h30,13h30,14h30,15h00,15h45,16h05,16h30,16h50,17h10,18h20,19h05,19h30,20h30,21h30,22h30,23h30,23h45,23h50,23h55</column>
        </table>
        <table name="times">
            <column name="station">Saint-Dorothee</column>
            <column name="direction">Deux-Montagnes</column>
            <column name="times_string">00h30,06h45,08h45,09h30,10h30,11h30,12h30,13h30,14h30,15h00,15h45,16h05,16h30,16h50,17h10,18h20,19h05,19h30,20h30,21h30,22h30,23h30,23h45,23h50,23h55</column>
        </table>
        <table name="times">
            <column name="station">Grand-Moulin</column>
            <column name="direction">Deux-Montagnes</column>
            <column name="times_string">00h30,06h45,08h45,09h30,10h30,11h30,12h30,13h30,14h30,15h00,15h45,16h05,16h30,16h50,17h10,18h20,19h05,19h30,20h30,21h30,22h30,23h30,23h45,23h50,23h55</column>
        </table>
        <table name="times">
            <column name="station">Deux-Montagnes</column>
            <column name="direction">Gare-Centrale</column>
            <column name="times_string">00h35,06h40,08h50,09h45,10h45,11h25,12h40,13h35,14h35,15h05,15h50,16h10,16h40,16h45,17h20,18h30,19h15,19h35,20h40,21h40,22h35,22h40,23h10,23h40,23h55</column>
        </table>
        <table name="times">
            <column name="station">Grand-Moulin</column>
            <column name="direction">Gare-Centrale</column>
            <column name="times_string">00h35,06h40,08h50,09h45,10h45,11h25,12h40,13h35,14h35,15h05,15h50,16h10,16h40,16h45,17h20,18h30,19h15,19h35,20h40,21h40,22h35,22h40,23h10,23h40,23h55</column>
        </table>
        <table name="times">
            <column name="station">Saint-Dorothee</column>
            <column name="direction">Gare-Centrale</column>
            <column name="times_string">00h35,06h40,08h50,09h45,10h45,11h25,12h40,13h35,14h35,15h05,15h50,16h10,16h40,16h45,17h20,18h30,19h15,19h35,20h40,21h40,22h35,22h40,23h10,23h40,23h55</column>
        </table>
        <table name="times">
            <column name="station">Ile-Bigras</column>
            <column name="direction">Gare-Centrale</column>
            <column name="times_string">00h35,06h40,08h50,09h45,10h45,11h25,12h40,13h35,14h35,15h05,15h50,16h10,16h40,16h45,17h20,18h30,19h15,19h35,20h40,21h40,22h35,22h40,23h10,23h40,23h55</column>
        </table>
        <table name="times">
            <column name="station">Roxboro-Pierrefonds</column>
            <column name="direction">Gare-Centrale</column>
            <column name="times_string">00h35,06h40,08h50,09h45,10h45,11h25,12h40,13h35,14h35,15h05,15h50,16h10,16h40,16h45,17h20,18h30,19h15,19h35,20h40,21h40,22h35,22h40,23h10,23h40,23h55</column>
        </table>
        <table name="times">
            <column name="station">Sunnybrooke</column>
            <column name="direction">Gare-Centrale</column>
            <column name="times_string">00h35,06h40,08h50,09h45,10h45,11h25,12h40,13h35,14h35,15h05,15h50,16h10,16h40,16h45,17h20,18h30,19h15,19h35,20h40,21h40,22h35,22h40,23h10,23h40,23h55</column>
        </table>
        <table name="times">
            <column name="station">Bois-Franc</column>
            <column name="direction">Gare-Centrale</column>
            <column name="times_string">00h35,06h40,08h50,09h45,10h45,11h25,12h40,13h35,14h35,15h05,15h50,16h10,16h40,16h45,17h20,18h30,19h15,19h35,20h40,21h40,22h35,22h40,23h10,23h40,23h55</column>
        </table>
        <table name="times">
            <column name="station">Du Ruisseau</column>
            <column name="direction">Gare-Centrale</column>
            <column name="times_string">00h35,06h40,08h50,09h45,10h45,11h25,12h40,13h35,14h35,15h05,15h50,16h10,16h40,16h45,17h20,18h30,19h15,19h35,20h40,21h40,22h35,22h40,23h10,23h40,23h55</column>
        </table>
        <table name="times">
            <column name="station">Montpelier</column>
            <column name="direction">Gare-Centrale</column>
            <column name="times_string">00h35,06h40,08h50,09h45,10h45,11h25,12h40,13h35,14h35,15h05,15h50,16h10,16h40,16h45,17h20,18h30,19h15,19h35,20h40,21h40,22h35,22h40,23h10,23h40,23h55</column>
        </table>
        <table name="times">
            <column name="station">Mont-Royal</column>
            <column name="direction">Gare-Centrale</column>
            <column name="times_string">00h35,06h40,08h50,09h45,10h45,11h25,12h40,13h35,14h35,15h05,15h50,16h10,16h40,16h45,17h20,18h30,19h15,19h35,20h40,21h40,22h35,22h40,23h10,23h40,23h55</column>
        </table>
        <table name="times">
            <column name="station">Canora</column>
            <column name="direction">Gare-Centrale</column>
            <column name="times_string">00h35,06h40,08h50,09h45,10h45,11h25,12h40,13h35,14h35,15h05,15h50,16h10,16h40,16h45,17h20,18h30,19h15,19h35,20h40,21h40,22h35,22h40,23h10,23h40,23h55</column>
        </table>
        <table name="times">
            <column name="station">Lucien-L'Allier</column>
            <column name="direction">Hudson</column>
            <column name="times_string">00h30,06h45,08h45,09h30,10h30,11h30,12h30,13h30,14h30,15h00,15h45,16h05,16h30,16h50,17h10,18h20,19h05,19h30,20h30,21h30,22h30,23h30,23h45,23h50,23h55</column>
        </table>
        <table name="times">
            <column name="station">Vendome</column>
            <column name="direction">Hudson</column>
            <column name="times_string">00h30,06h45,08h45,09h30,10h30,11h30,12h30,13h30,14h30,15h00,15h45,16h05,16h30,16h50,17h10,18h20,19h05,19h30,20h30,21h30,22h30,23h30,23h45,23h50,23h55</column>
        </table>
        <table name="times">
            <column name="station">Montreal-Ouest</column>
            <column name="direction">Hudson</column>
            <column name="times_string">00h30,06h45,08h45,09h30,10h30,11h30,12h30,13h30,14h30,15h00,15h45,16h05,16h30,16h50,17h10,18h20,19h05,19h30,20h30,21h30,22h30,23h30,23h45,23h50,23h55</column>
        </table>
        <table name="times">
            <column name="station">Lachine</column>
            <column name="direction">Hudson</column>
            <column name="times_string">00h30,06h45,08h45,09h30,10h30,11h30,12h30,13h30,14h30,15h00,15h45,16h05,16h30,16h50,17h10,18h20,19h05,19h30,20h30,21h30,22h30,23h30,23h45,23h50,23h55</column>
        </table>
        <table name="times">
            <column name="station">Dorval</column>
            <column name="direction">Hudson</column>
            <column name="times_string">00h30,06h45,08h45,09h30,10h30,11h30,12h30,13h30,14h30,15h00,15h45,16h05,16h30,16h50,17h10,18h20,19h05,19h30,20h30,21h30,22h30,23h30,23h45,23h50,23h55</column>
        </table>
        <table name="times">
            <column name="station">Pine Beach</column>
            <column name="direction">Hudson</column>
            <column name="times_string">00h30,06h45,08h45,09h30,10h30,11h30,12h30,13h30,14h30,15h00,15h45,16h05,16h30,16h50,17h10,18h20,19h05,19h30,20h30,21h30,22h30,23h30,23h45,23h50,23h55</column>
        </table>
        <table name="times">
            <column name="station">Valois</column>
            <column name="direction">Hudson</column>
            <column name="times_string">00h30,06h45,08h45,09h30,10h30,11h30,12h30,13h30,14h30,15h00,15h45,16h05,16h30,16h50,17h10,18h20,19h05,19h30,20h30,21h30,22h30,23h30,23h45,23h50,23h55</column>
        </table>
        <table name="times">
            <column name="station">Pointe-Claire</column>
            <column name="direction">Hudson</column>
            <column name="times_string">00h30,06h45,08h45,09h30,10h30,11h30,12h30,13h30,14h30,15h00,15h45,16h05,16h30,16h50,17h10,18h20,19h05,19h30,20h30,21h30,22h30,23h30,23h45,23h50,23h55</column>
        </table>
        <table name="times">
            <column name="station">Cedar Park</column>
            <column name="direction">Hudson</column>
            <column name="times_string">00h30,06h45,08h45,09h30,10h30,11h30,12h30,13h30,14h30,15h00,15h45,16h05,16h30,16h50,17h10,18h20,19h05,19h30,20h30,21h30,22h30,23h30,23h45,23h50,23h55</column>
        </table>
        <table name="times">
            <column name="station">Beaconsfield</column>
            <column name="direction">Hudson</column>
            <column name="times_string">00h30,06h45,08h45,09h30,10h30,11h30,12h30,13h30,14h30,15h00,15h45,16h05,16h30,16h50,17h10,18h20,19h05,19h30,20h30,21h30,22h30,23h30,23h45,23h50,23h55</column>
        </table>
        <table name="times">
            <column name="station">Beaurepaire</column>
            <column name="direction">Hudson</column>
            <column name="times_string">00h30,06h45,08h45,09h30,10h30,11h30,12h30,13h30,14h30,15h00,15h45,16h05,16h30,16h50,17h10,18h20,19h05,19h30,20h30,21h30,22h30,23h30,23h45,23h50,23h55</column>
        </table>
        <table name="times">
            <column name="station">Baie-D'Urfe</column>
            <column name="direction">Hudson</column>
            <column name="times_string">00h30,06h45,08h45,09h30,10h30,11h30,12h30,13h30,14h30,15h00,15h45,16h05,16h30,16h50,17h10,18h20,19h05,19h30,20h30,21h30,22h30,23h30,23h45,23h50,23h55</column>
        </table>
        <table name="times">
            <column name="station">Sainte-Anne-de-Bellevue</column>
            <column name="direction">Hudson</column>
            <column name="times_string">00h30,06h45,08h45,09h30,10h30,11h30,12h30,13h30,14h30,15h00,15h45,16h05,16h30,16h50,17h10,18h20,19h05,19h30,20h30,21h30,22h30,23h30,23h45,23h50,23h55</column>
        </table>
        <table name="times">
            <column name="station">Ile-Perrot</column>
            <column name="direction">Hudson</column>
            <column name="times_string">00h30,06h45,08h45,09h30,10h30,11h30,12h30,13h30,14h30,15h00,15h45,16h05,16h30,16h50,17h10,18h20,19h05,19h30,20h30,21h30,22h30,23h30,23h45,23h50,23h55</column>
        </table>
        <table name="times">
            <column name="station">Pincourt–Terrasse-Vaudreuil</column>
            <column name="direction">Hudson</column>
            <column name="times_string">00h30,06h45,08h45,09h30,10h30,11h30,12h30,13h30,14h30,15h00,15h45,16h05,16h30,16h50,17h10,18h20,19h05,19h30,20h30,21h30,22h30,23h30,23h45,23h50,23h55</column>
        </table>
        <table name="times">
            <column name="station">Dorion</column>
            <column name="direction">Hudson</column>
            <column name="times_string">00h30,06h45,08h45,09h30,10h30,11h30,12h30,13h30,14h30,15h00,15h45,16h05,16h30,16h50,17h10,18h20,19h05,19h30,20h30,21h30,22h30,23h30,23h45,23h50,23h55</column>
        </table>
        <table name="times">
            <column name="station">Vaudreuil</column>
            <column name="direction">Hudson</column>
            <column name="times_string">00h30,06h45,08h45,09h30,10h30,11h30,12h30,13h30,14h30,15h00,15h45,16h05,16h30,16h50,17h10,18h20,19h05,19h30,20h30,21h30,22h30,23h30,23h45,23h50,23h55</column>
        </table>
        <table name="times">
            <column name="station">Hudson</column>
            <column name="direction">Lucien-L'Allier</column>
            <column name="times_string">00h35,06h40,08h50,09h45,10h45,11h25,12h40,13h35,14h35,15h05,15h50,16h10,16h40,16h45,17h20,18h30,19h15,19h35,20h40,21h40,22h35,22h40,23h10,23h40,23h55</column>
        </table>
        <table name="times">
            <column name="station">Vaudreuil</column>
            <column name="direction">Lucien-L'Allier</column>
            <column name="times_string">00h35,06h40,08h50,09h45,10h45,11h25,12h40,13h35,14h35,15h05,15h50,16h10,16h40,16h45,17h20,18h30,19h15,19h35,20h40,21h40,22h35,22h40,23h10,23h40,23h55</column>
        </table>
        <table name="times">
            <column name="station">Dorion</column>
            <column name="direction">Lucien-L'Allier</column>
            <column name="times_string">00h35,06h40,08h50,09h45,10h45,11h25,12h40,13h35,14h35,15h05,15h50,16h10,16h40,16h45,17h20,18h30,19h15,19h35,20h40,21h40,22h35,22h40,23h10,23h40,23h55</column>
        </table>
        <table name="times">
            <column name="station">Pincourt–Terrasse-Vaudreuil</column>
            <column name="direction">Lucien-L'Allier</column>
            <column name="times_string">00h35,06h40,08h50,09h45,10h45,11h25,12h40,13h35,14h35,15h05,15h50,16h10,16h40,16h45,17h20,18h30,19h15,19h35,20h40,21h40,22h35,22h40,23h10,23h40,23h55</column>
        </table>
        <table name="times">
            <column name="station">Ile-Perrot</column>
            <column name="direction">Lucien-L'Allier</column>
            <column name="times_string">00h35,06h40,08h50,09h45,10h45,11h25,12h40,13h35,14h35,15h05,15h50,16h10,16h40,16h45,17h20,18h30,19h15,19h35,20h40,21h40,22h35,22h40,23h10,23h40,23h55</column>
        </table>
        <table name="times">
            <column name="station">Sainte-Anne-de-Bellevue</column>
            <column name="direction">Lucien-L'Allier</column>
            <column name="times_string">00h35,06h40,08h50,09h45,10h45,11h25,12h40,13h35,14h35,15h05,15h50,16h10,16h40,16h45,17h20,18h30,19h15,19h35,20h40,21h40,22h35,22h40,23h10,23h40,23h55</column>
        </table>
        <table name="times">
            <column name="station">Baie-D'Urfe</column>
            <column name="direction">Lucien-L'Allier</column>
            <column name="times_string">00h35,06h40,08h50,09h45,10h45,11h25,12h40,13h35,14h35,15h05,15h50,16h10,16h40,16h45,17h20,18h30,19h15,19h35,20h40,21h40,22h35,22h40,23h10,23h40,23h55</column>
        </table>
        <table name="times">
            <column name="station">Beaurepaire</column>
            <column name="direction">Lucien-L'Allier</column>
            <column name="times_string">00h35,06h40,08h50,09h45,10h45,11h25,12h40,13h35,14h35,15h05,15h50,16h10,16h40,16h45,17h20,18h30,19h15,19h35,20h40,21h40,22h35,22h40,23h10,23h40,23h55</column>
        </table>
        <table name="times">
            <column name="station">Beaconsfield</column>
            <column name="direction">Lucien-L'Allier</column>
            <column name="times_string">00h35,06h40,08h50,09h45,10h45,11h25,12h40,13h35,14h35,15h05,15h50,16h10,16h40,16h45,17h20,18h30,19h15,19h35,20h40,21h40,22h35,22h40,23h10,23h40,23h55</column>
        </table>
        <table name="times">
            <column name="station">Cedar Park</column>
            <column name="direction">Lucien-L'Allier</column>
            <column name="times_string">00h35,06h40,08h50,09h45,10h45,11h25,12h40,13h35,14h35,15h05,15h50,16h10,16h40,16h45,17h20,18h30,19h15,19h35,20h40,21h40,22h35,22h40,23h10,23h40,23h55</column>
        </table>
        <table name="times">
            <column name="station">Pointe-Claire</column>
            <column name="direction">Lucien-L'Allier</column>
            <column name="times_string">00h35,06h40,08h50,09h45,10h45,11h25,12h40,13h35,14h35,15h05,15h50,16h10,16h40,16h45,17h20,18h30,19h15,19h35,20h40,21h40,22h35,22h40,23h10,23h40,23h55</column>
        </table>
        <table name="times">
            <column name="station">Valois</column>
            <column name="direction">Lucien-L'Allier</column>
            <column name="times_string">00h35,06h40,08h50,09h45,10h45,11h25,12h40,13h35,14h35,15h05,15h50,16h10,16h40,16h45,17h20,18h30,19h15,19h35,20h40,21h40,22h35,22h40,23h10,23h40,23h55</column>
        </table>
        <table name="times">
            <column name="station">Pine Beach</column>
            <column name="direction">Lucien-L'Allier</column>
            <column name="times_string">00h35,06h40,08h50,09h45,10h45,11h25,12h40,13h35,14h35,15h05,15h50,16h10,16h40,16h45,17h20,18h30,19h15,19h35,20h40,21h40,22h35,22h40,23h10,23h40,23h55</column>
        </table>
        <table name="times">
            <column name="station">Dorval</column>
            <column name="direction">Lucien-L'Allier</column>
            <column name="times_string">00h35,06h40,08h50,09h45,10h45,11h25,12h40,13h35,14h35,15h05,15h50,16h10,16h40,16h45,17h20,18h30,19h15,19h35,20h40,21h40,22h35,22h40,23h10,23h40,23h55</column>
        </table>
        <table name="times">
            <column name="station">Lachine</column>
            <column name="direction">Lucien-L'Allier</column>
            <column name="times_string">00h35,06h40,08h50,09h45,10h45,11h25,12h40,13h35,14h35,15h05,15h50,16h10,16h40,16h45,17h20,18h30,19h15,19h35,20h40,21h40,22h35,22h40,23h10,23h40,23h55</column>
        </table>
        <table name="times">
            <column name="station">Montreal-Ouest</column>
            <column name="direction">Lucien-L'Allier</column>
            <column name="times_string">00h35,06h40,08h50,09h45,10h45,11h25,12h40,13h35,14h35,15h05,15h50,16h10,16h40,16h45,17h20,18h30,19h15,19h35,20h40,21h40,22h35,22h40,23h10,23h40,23h55</column>
        </table>
        <table name="times">
            <column name="station">Vendome</column>
            <column name="direction">Lucien-L'Allier</column>
            <column name="times_string">00h35,06h40,08h50,09h45,10h45,11h25,12h40,13h35,14h35,15h05,15h50,16h10,16h40,16h45,17h20,18h30,19h15,19h35,20h40,21h40,22h35,22h40,23h10,23h40,23h55</column>
        </table>
        <table name="times">
            <column name="station">Lucien-L'Allier</column>
            <column name="direction">Candiac</column>
            <column name="times_string">00h30,06h45,08h45,09h30,10h30,11h30,12h30,13h30,14h30,15h00,15h45,16h05,16h30,16h50,17h10,18h20,19h05,19h30,20h30,21h30,22h30,23h30,23h45,23h50,23h55</column>
        </table>
        <table name="times">
            <column name="station">Vendome</column>
            <column name="direction">Candiac</column>
            <column name="times_string">00h30,06h45,08h45,09h30,10h30,11h30,12h30,13h30,14h30,15h00,15h45,16h05,16h30,16h50,17h10,18h20,19h05,19h30,20h30,21h30,22h30,23h30,23h45,23h50,23h55</column>
        </table>
        <table name="times">
            <column name="station">Montreal-Ouest</column>
            <column name="direction">Candiac</column>
            <column name="times_string">00h30,06h45,08h45,09h30,10h30,11h30,12h30,13h30,14h30,15h00,15h45,16h05,16h30,16h50,17h10,18h20,19h05,19h30,20h30,21h30,22h30,23h30,23h45,23h50,23h55</column>
        </table>
        <table name="times">
            <column name="station">Montreal-Ouest</column>
            <column name="direction">Lucien-L'Allier</column>
            <column name="times_string">00h35,06h40,08h50,09h45,10h45,11h25,12h40,13h35,14h35,15h05,15h50,16h10,16h40,16h45,17h20,18h30,19h15,19h35,20h40,21h40,22h35,22h40,23h10,23h40,23h55</column>
        </table>
        <table name="times">
            <column name="station">Vendome</column>
            <column name="direction">Lucien-L'Allier</column>
            <column name="times_string">00h35,06h40,08h50,09h45,10h45,11h25,12h40,13h35,14h35,15h05,15h50,16h10,16h40,16h45,17h20,18h30,19h15,19h35,20h40,21h40,22h35,22h40,23h10,23h40,23h55</column>
        </table>
        <!-- Table users -->
        <table name="users">
            <column name="firstname">Annette</column>
            <column name="lastname">Couto</column>
            <column name="address">446 Spring Garden</column>
            <column name="city">Sao Paulo</column>
            <column name="province">Quebec</column>
            <column name="postal">H9B 1S8</column>
            <column name="email">acouto@lbpsb.qc.ca</column>
            <column name="phone1">514 673 6452</column>
            <column name="phone2">514 784 6424</column>
            <column name="birthday">1957-08-06</column>
            <column name="username">acouto5</column>
            <column name="password">12345</column>
            <column name="cpassword">12345</column>
            <column name="zone">2</column>
            <column name="carpool">0</column>
            <column name="carpoolBuddies">NULL</column>
        </table>
        <table name="users">
            <column name="firstname">Carlod</column>
            <column name="lastname">Venturaq</column>
            <column name="address">671 Grey Zone</column>
            <column name="city">Montreal</column>
            <column name="province">Quebec</column>
            <column name="postal">H8Y 1C2</column>
            <column name="email">ventura53@gmail.com</column>
            <column name="phone1">514 724 9012</column>
            <column name="phone2">672 513 7214</column>
            <column name="birthday">1990-10-11</column>
            <column name="username">ceventura2</column>
            <column name="password">1652</column>
            <column name="cpassword">1652</column>
            <column name="zone">3</column>
            <column name="carpool">1</column>
            <column name="carpoolBuddies">NULL</column>
        </table>
        <table name="users">
            <column name="firstname">what</column>
            <column name="lastname">what</column>
            <column name="address">whatff</column>
            <column name="city">what</column>
            <column name="province">no</column>
            <column name="postal">a2n 3n2</column>
            <column name="email">0hewr@xxx.com</column>
            <column name="phone1">234 234 2344</column>
            <column name="phone2"></column>
            <column name="birthday">2005-08-11</column>
            <column name="username">Demostenis</column>
            <column name="password">abc123</column>
            <column name="cpassword">abc123</column>
            <column name="zone">1</column>
            <column name="carpool">0</column>
            <column name="carpoolBuddies">NULL</column>
        </table>
        <table name="users">
            <column name="firstname">Dexter</column>
            <column name="lastname">Moore</column>
            <column name="address">8907 SAint-Cristophe</column>
            <column name="city">Montreal</column>
            <column name="province">QC</column>
            <column name="postal">P4V 8N9</column>
            <column name="email">mm@m.com</column>
            <column name="phone1">123 111 1114</column>
            <column name="phone2"></column>
            <column name="birthday">1990-01-04</column>
            <column name="username">dexy12</column>
            <column name="password">123</column>
            <column name="cpassword">123</column>
            <column name="zone">3</column>
            <column name="carpool">1</column>
            <column name="carpoolBuddies">jachan,lebron</column>
        </table>
        <table name="users">
            <column name="firstname">Mila</column>
            <column name="lastname">Hernandez</column>
            <column name="address">73 Hot</column>
            <column name="city">Chicago</column>
            <column name="province">Illinois</column>
            <column name="postal">J8U 7V5</column>
            <column name="email">hende24@gmail.com</column>
            <column name="phone1">907 873 6723</column>
            <column name="phone2">835 723 7823</column>
            <column name="birthday">2000-02-02</column>
            <column name="username">hedley1234</column>
            <column name="password">abcd5678</column>
            <column name="cpassword">abcd5678</column>
            <column name="zone">3</column>
            <column name="carpool">0</column>
            <column name="carpoolBuddies">NULL</column>
        </table>
        <table name="users">
            <column name="firstname">Owen</column>
            <column name="lastname">Hernandez</column>
            <column name="address">73 Hot</column>
            <column name="city">Chicago</column>
            <column name="province">Illinois</column>
            <column name="postal">J8U 7V5</column>
            <column name="email">hende24@gmail.com</column>
            <column name="phone1">907 873 6723</column>
            <column name="phone2">835 723 7823</column>
            <column name="birthday">1943-06-28</column>
            <column name="username">hende8923</column>
            <column name="password">6789</column>
            <column name="cpassword">6789</column>
            <column name="zone">3</column>
            <column name="carpool">1</column>
            <column name="carpoolBuddies">NULL</column>
        </table>
        <table name="users">
            <column name="firstname">sexy</column>
            <column name="lastname">mama</column>
            <column name="address">1234 mybutt</column>
            <column name="city">you</column>
            <column name="province">on</column>
            <column name="postal">M3B 4B7</column>
            <column name="email">sexy@hotmail.com</column>
            <column name="phone1">514 322 3232</column>
            <column name="phone2">400 232 2495</column>
            <column name="birthday">2004-12-08</column>
            <column name="username">heysexy</column>
            <column name="password">lolol</column>
            <column name="cpassword">lolol</column>
            <column name="zone">1</column>
            <column name="carpool">1</column>
            <column name="carpoolBuddies">NULL</column>
        </table>
        <table name="users">
            <column name="firstname">Jackie</column>
            <column name="lastname">Chan</column>
            <column name="address">0912 Road</column>
            <column name="city">Road</column>
            <column name="province">RD</column>
            <column name="postal">A1B 2C3</column>
            <column name="email">l@l.com</column>
            <column name="phone1">123 123 1234</column>
            <column name="phone2">123 123 1234</column>
            <column name="birthday">2003-03-03</column>
            <column name="username">jachan</column>
            <column name="password">abc1234</column>
            <column name="cpassword">abc1234</column>
            <column name="zone">1</column>
            <column name="carpool">1</column>
            <column name="carpoolBuddies">NULL</column>
        </table>
        <table name="users">
            <column name="firstname">Jorge</column>
            <column name="lastname">Correira</column>
            <column name="address">621 Grit Bot</column>
            <column name="city">Toronto</column>
            <column name="province">Ontario</column>
            <column name="postal">K9G 5Y7</column>
            <column name="email">jorgebut@hotmail.com</column>
            <column name="phone1">934 752 9814</column>
            <column name="phone2">934 671 7824</column>
            <column name="birthday">1964-03-05</column>
            <column name="username">jorgeb65</column>
            <column name="password">1091</column>
            <column name="cpassword">1091</column>
            <column name="zone">3</column>
            <column name="carpool">1</column>
            <column name="carpoolBuddies">NULL</column>
        </table>
        <table name="users">
            <column name="firstname">Kyle</column>
            <column name="lastname">Ventura</column>
            <column name="address">152 Athenes</column>
            <column name="city">Rio</column>
            <column name="province">Montreal</column>
            <column name="postal">J8T 5D2</column>
            <column name="email">vent62@yahoo.com</column>
            <column name="phone1">901 521 7612</column>
            <column name="phone2">901 672 7623</column>
            <column name="birthday">1998-12-11</column>
            <column name="username">kyle12</column>
            <column name="password">1761</column>
            <column name="cpassword">1761</column>
            <column name="zone">3</column>
            <column name="carpool">0</column>
            <column name="carpoolBuddies">NULL</column>
        </table>
        <table name="users">
            <column name="firstname">Miranda</column>
            <column name="lastname">Larroza</column>
            <column name="address">87 Mentana</column>
            <column name="city">Bramptom</column>
            <column name="province">Montreal</column>
            <column name="postal">K9D 5S3</column>
            <column name="email">larry52@gmail.com</column>
            <column name="phone1">903 762 6723</column>
            <column name="phone2">904 672 4523</column>
            <column name="birthday">1992-06-12</column>
            <column name="username">larr671</column>
            <column name="password">8901</column>
            <column name="cpassword">8901</column>
            <column name="zone">1</column>
            <column name="carpool">1</column>
            <column name="carpoolBuddies">NULL</column>
        </table>
        <table name="users">
            <column name="firstname">LeBron</column>
            <column name="lastname">James</column>
            <column name="address">1234 Cleveland</column>
            <column name="city">Cleveland</column>
            <column name="province">Ohio</column>
            <column name="postal">R2B 5Y5</column>
            <column name="email">lb@gmail.com</column>
            <column name="phone1">123 123 1234</column>
            <column name="phone2">123 123 1234</column>
            <column name="birthday">1991-01-07</column>
            <column name="username">lebron</column>
            <column name="password">abc123</column>
            <column name="cpassword">abc123</column>
            <column name="zone">1</column>
            <column name="carpool">1</column>
            <column name="carpoolBuddies">NULL</column>
        </table>
        <table name="users">
            <column name="firstname">Lenny</column>
            <column name="lastname">Dimanalata</column>
            <column name="address">4015 Saint-Andre</column>
            <column name="city">Montreal</column>
            <column name="province">QC</column>
            <column name="postal">H2L 3W2</column>
            <column name="email">lenny@l.com</column>
            <column name="phone1">123 123 1234</column>
            <column name="phone2">123 123 1234</column>
            <column name="birthday">1999-05-03</column>
            <column name="username">lenmor</column>
            <column name="password">markoj2049</column>
            <column name="cpassword">markoj2049</column>
            <column name="zone">1</column>
            <column name="carpool">1</column>
            <column name="carpoolBuddies">hende8923,heysexy,jachan</column>
        </table>
        <table name="users">
            <column name="firstname">Mandynga</column>
            <column name="lastname">Moore</column>
            <column name="address">8907 SAint-Cristophe</column>
            <column name="city">Montreal</column>
            <column name="province">QC</column>
            <column name="postal">P4V 8N9</column>
            <column name="email">mm@m.com</column>
            <column name="phone1">123 111 1114</column>
            <column name="phone2"></column>
            <column name="birthday">1990-01-04</column>
            <column name="username">mandymm</column>
            <column name="password">1234</column>
            <column name="cpassword">1234</column>
            <column name="zone">3</column>
            <column name="carpool">1</column>
            <column name="carpoolBuddies">NULL</column>
        </table>
        <table name="users">
            <column name="firstname">Marie</column>
            <column name="lastname">Digby</column>
            <column name="address">4546 Golden State</column>
            <column name="city">GS2</column>
            <column name="province">GS</column>
            <column name="postal">A1B 2C3</column>
            <column name="email">m@ma.com</column>
            <column name="phone1">123 123 1234</column>
            <column name="phone2"></column>
            <column name="birthday">2004-02-01</column>
            <column name="username">marie23</column>
            <column name="password">abc123</column>
            <column name="cpassword">abc123</column>
            <column name="zone">2</column>
            <column name="carpool">1</column>
            <column name="carpoolBuddies">jorgeb65,larr671,lebron,lenmor</column>
        </table>
        <table name="users">
            <column name="firstname">Maria</column>
            <column name="lastname">Magdalene</column>
            <column name="address">188 Monny</column>
            <column name="city">Mon</column>
            <column name="province">QC</column>
            <column name="postal">B7B 6H2</column>
            <column name="email">l@l.cpp</column>
            <column name="phone1">123 111 1111</column>
            <column name="phone2"></column>
            <column name="birthday">1992-02-14</column>
            <column name="username">peter34</column>
            <column name="password">123</column>
            <column name="cpassword">123</column>
            <column name="zone">3</column>
            <column name="carpool">0</column>
            <column name="carpoolBuddies">NULL</column>
        </table>
        <table name="users">
            <column name="firstname">marivi</column>
            <column name="lastname">Magdalene</column>
            <column name="address">188 Monny</column>
            <column name="city">Mon</column>
            <column name="province">QC</column>
            <column name="postal">B7B 6H2</column>
            <column name="email">l@l.cpp</column>
            <column name="phone1">123 111 1111</column>
            <column name="phone2"></column>
            <column name="birthday">1992-02-14</column>
            <column name="username">peter78</column>
            <column name="password">12345</column>
            <column name="cpassword">12345</column>
            <column name="zone">3</column>
            <column name="carpool">0</column>
            <column name="carpoolBuddies">NULL</column>
        </table>
        <table name="users">
            <column name="firstname">Mandy</column>
            <column name="lastname">Moore</column>
            <column name="address">8907 SAint-Cristophe</column>
            <column name="city">Montreal</column>
            <column name="province">QC</column>
            <column name="postal">P4V 8N9</column>
            <column name="email">mm@m.com</column>
            <column name="phone1">123 111 1114</column>
            <column name="phone2"></column>
            <column name="birthday">1990-01-04</column>
            <column name="username">polenta</column>
            <column name="password">asd</column>
            <column name="cpassword">asd</column>
            <column name="zone">2</column>
            <column name="carpool">0</column>
            <column name="carpoolBuddies">NULL</column>
        </table>
        <table name="users">
            <column name="firstname">Mandy</column>
            <column name="lastname">Moore</column>
            <column name="address">8907 SAint-Cristophe</column>
            <column name="city">Montreal</column>
            <column name="province">QC</column>
            <column name="postal">P4V 8N9</column>
            <column name="email">mm@m.com</column>
            <column name="phone1">123 111 1114</column>
            <column name="phone2"></column>
            <column name="birthday">1990-01-04</column>
            <column name="username">polenta12</column>
            <column name="password">123</column>
            <column name="cpassword">123</column>
            <column name="zone">2</column>
            <column name="carpool">0</column>
            <column name="carpoolBuddies">NULL</column>
        </table>
        <table name="users">
            <column name="firstname">WAhahadsdsa</column>
            <column name="lastname">Hernandez</column>
            <column name="address">73 Hot</column>
            <column name="city">Chicago</column>
            <column name="province">Illinois</column>
            <column name="postal">J8U 7V5</column>
            <column name="email">hende24@gmail.com</column>
            <column name="phone1">907 873 6723</column>
            <column name="phone2">835 723 7823</column>
            <column name="birthday">2002-03-06</column>
            <column name="username">rareqw123</column>
            <column name="password">aaa</column>
            <column name="cpassword">aaa</column>
            <column name="zone">3</column>
            <column name="carpool">1</column>
            <column name="carpoolBuddies">NULL</column>
        </table>
        <table name="users">
            <column name="firstname">Elise</column>
            <column name="lastname">Sanchez</column>
            <column name="address">43 Fox</column>
            <column name="city">Pierrefonds</column>
            <column name="province">Ontario</column>
            <column name="postal">N8Y 6F4</column>
            <column name="email">eli82@gmail.com</column>
            <column name="phone1">873 652 3412</column>
            <column name="phone2">762 651 6723</column>
            <column name="birthday">1993-06-14</column>
            <column name="username">sanche54</column>
            <column name="password">8923</column>
            <column name="cpassword">8923</column>
            <column name="zone">3</column>
            <column name="carpool">1</column>
            <column name="carpoolBuddies">NULL</column>
        </table>
        <table name="users">
            <column name="firstname">Stephen</column>
            <column name="lastname">Curry</column>
            <column name="address">4546 Golden State</column>
            <column name="city">GS</column>
            <column name="province">California</column>
            <column name="postal">R2N 5Y6</column>
            <column name="email">sc@gmail.com</column>
            <column name="phone1">123 123 1234</column>
            <column name="phone2">123 123 1234</column>
            <column name="birthday">1977-03-10</column>
            <column name="username">stephc</column>
            <column name="password">abc124</column>
            <column name="cpassword">abc124</column>
            <column name="zone">1</column>
            <column name="carpool">1</column>
            <column name="carpoolBuddies">dexy12,hende8923,jorgeb65,larr671</column>
        </table>
    </database>
</pma_xml_export>